{"cameraMode":{"drawMode":0,"name":"Shaded","section":"Shading Mode"},"sceneLighting":false,"audioPlay":false,"sceneViewState":{"m_AlwaysRefresh":false,"showFog":true,"showSkybox":false,"showFlares":true,"showImageEffects":true,"showParticleSystems":true,"showVisualEffectGraphs":true,"m_FxEnabled":true},"in2DMode":false,"pivot":{"x":7.015000343322754,"y":0.0,"z":-9.984999656677246},"rotation":{"x":-0.36181288957595827,"y":-0.6150053143501282,"z":0.3770371973514557,"w":-0.5903837084770203},"size":19.054637908935548,"orthographic":false}